letter_tools/__init__.py
letter_tools-0.2.4.dist-info/LICENSE
letter_tools-0.2.4.dist-info/METADATA
letter_tools-0.2.4.dist-info/WHEEL
letter_tools-0.2.4.dist-info/top_level.txt
letter_tools-0.2.4.dist-info/RECORD
