Metadata-Version: 2.1
Name: letter-tools
Version: 0.2.4
Summary: Python tools for doing stuff with letters.
Home-page: https://github.com/hostedposted/letter-tools
Author: Hostedposted
Author-email: hostedpostedsite@gmail.com
License: UNKNOWN
Platform: UNKNOWN
Classifier: Programming Language :: Python
Classifier: Programming Language :: Python :: 2
Classifier: Programming Language :: Python :: 2.7
Classifier: Programming Language :: Python :: 3
Classifier: Programming Language :: Python :: 3.5
Classifier: Programming Language :: Python :: 3.6
Classifier: Programming Language :: Python :: 3.7
Classifier: Programming Language :: Python :: 3.8
Classifier: License :: OSI Approved :: MIT License
Classifier: Operating System :: OS Independent
Requires-Python: >=2.7
Requires-Dist: requests (>=2.25.0)
